pyramid_sqlalchemy_continuum3/__init__.py
pyramid_sqlalchemy_continuum3/plugin.py
pyramid_sqlalchemy_continuum3-1.0.2.dist-info/LICENSE
pyramid_sqlalchemy_continuum3-1.0.2.dist-info/METADATA
pyramid_sqlalchemy_continuum3-1.0.2.dist-info/WHEEL
pyramid_sqlalchemy_continuum3-1.0.2.dist-info/top_level.txt
pyramid_sqlalchemy_continuum3-1.0.2.dist-info/RECORD
