Metadata-Version: 2.1
Name: pyramid-sqlalchemy-continuum3
Version: 1.0.2
Summary: PyramidPlugin offers way of integrating Pyramid framework with SQLAlchemy-Continuum.
Home-page: https://github.com/HAASLEWER/pyramid_sqlalchemy_continuum
Author: Lehan Coetzee (Jordi Fernández <jfernandez@bioiberica.com>)
Author-email: haaslewer2@gmail.com
License: UNKNOWN
Platform: UNKNOWN
Classifier: Programming Language :: Python :: 3
Classifier: License :: OSI Approved :: MIT License
Classifier: Operating System :: OS Independent
Requires-Python: >=3.6
